odoo10_addon_donation_thanks-10.0.1.0.0.99.dev12-py2.7-nspkg.pth
odoo/addons/donation_thanks/README.rst
odoo/addons/donation_thanks/__init__.py
odoo/addons/donation_thanks/__manifest__.py
odoo/addons/donation_thanks/i18n/de.po
odoo/addons/donation_thanks/i18n/donation_thanks.pot
odoo/addons/donation_thanks/i18n/fr.po
odoo/addons/donation_thanks/models/__init__.py
odoo/addons/donation_thanks/models/donation.py
odoo/addons/donation_thanks/models/donation_thanks_template.py
odoo/addons/donation_thanks/report/report_thanks.xml
odoo/addons/donation_thanks/report/thanks.odt
odoo/addons/donation_thanks/security/donation_security.xml
odoo/addons/donation_thanks/security/ir.model.access.csv
odoo/addons/donation_thanks/static/description/icon.png
odoo/addons/donation_thanks/views/donation.xml
odoo/addons/donation_thanks/views/donation_thanks_template.xml
odoo10_addon_donation_thanks-10.0.1.0.0.99.dev12.dist-info/METADATA
odoo10_addon_donation_thanks-10.0.1.0.0.99.dev12.dist-info/RECORD
odoo10_addon_donation_thanks-10.0.1.0.0.99.dev12.dist-info/WHEEL
odoo10_addon_donation_thanks-10.0.1.0.0.99.dev12.dist-info/namespace_packages.txt
odoo10_addon_donation_thanks-10.0.1.0.0.99.dev12.dist-info/top_level.txt
